{
    "title": "Политика Конфиденциальности",
    "lastUpdated": "Последнее обновление: 15 Января 2024",
    "sections": [
        {
            "title": "Введение",
            "content": "NovaAI («мы», «наш» или «нас») обязуется защищать вашу конфиденциальность. Эта Политика Конфиденциальности объясняет, как мы собираем, используем, раскрываем и защищаем вашу информацию, когда вы посещаете наш веб-сайт или используете наши услуги."
        },
        {
            "title": "Информация, которую мы собираем",
            "subsections": [
                {
                    "title": "Личная Информация",
                    "content": "Мы можем собирать личную информацию, которую вы добровольно предоставляете нам, когда вы:",
                    "list": [
                        "Связываетесь с нами через наш сайт",
                        "Подписываетесь на нашу рассылку",
                        "Запрашиваете информацию о наших услугах",
                        "Подаете заявку на вакансию"
                    ],
                    "footer": "Эта информация может включать ваше имя, адрес электронной почты, номер телефона, название компании и любую другую информацию, которую вы решите предоставить."
                },
                {
                    "title": "Автоматически Собираемая Информация",
                    "content": "При посещении нашего веб-сайта мы можем автоматически собирать определенную информацию о вашем устройстве, включая:",
                    "list": [
                        "IP-адрес",
                        "Тип браузера и версия",
                        "Операционная система",
                        "Посещенные страницы и время",
                        "Адрес ссылающегося сайта"
                    ]
                }
            ]
        },
        {
            "title": "Как мы используем вашу информацию",
            "content": "Мы можем использовать собранную информацию для следующих целей:",
            "list": [
                "Ответ на ваши запросы",
                "Предоставление наших услуг",
                "Отправка маркетинговых сообщений (с вашего согласия)",
                "Улучшение нашего веб-сайта и услуг",
                "Анализ моделей использования",
                "Соблюдение юридических обязательств"
            ]
        },
        {
            "title": "Передача вашей информации",
            "content": "Мы не продаем вашу личную информацию. Мы можем передавать вашу информацию:",
            "list": [
                "Поставщикам услуг, которые помогают нам в работе",
                "Профессиональным консультантам (юристам, бухгалтерам)",
                "Государственным органам, когда это требуется по закону",
                "Бизнес-партнерам (с вашего согласия)"
            ]
        },
        {
            "title": "Безопасность данных",
            "content": "Мы внедряем соответствующие технические и организационные меры для защиты вашей личной информации от несанкционированного доступа, изменения, раскрытия или уничтожения."
        },
        {
            "title": "Ваши права",
            "content": "В зависимости от вашего местоположения вы можете иметь права, включая:",
            "list": [
                "Доступ к вашей личной информации",
                "Исправление неточных данных",
                "Удаление ваших данных",
                "Ограничение обработки",
                "Переносимость данных",
                "Возражение против обработки"
            ]
        },
        {
            "title": "Cookies",
            "content": "Мы используем куки и аналогичные технологии отслеживания для сбора информации о вашей активности в браузере. Вы можете управлять настройками куки в своем браузере."
        },
        {
            "title": "Изменения в этой Политике",
            "content": "Мы можем время от времени обновлять эту Политику Конфиденциальности. Мы уведомим вас о любых изменениях, опубликовав новую политику на этой странице и обновив дату «Последнее обновление»."
        },
        {
            "title": "Свяжитесь с нами",
            "content": "Если у вас есть вопросы об этой Политике Конфиденциальности или нашей практике конфиденциальности, пожалуйста, свяжитесь с нами по адресу:\n\nEmail: privacy@novaai.com\nАдрес: 123 Innovation Drive, San Francisco, CA 94107"
        }
    ]
}